sparse_to_dense/__init__.py
sparse_to_dense/app.py
sparse_to_dense/core/manager.py
sparse_to_dense/core/timing.py
sparse_to_dense/dense/main.py
sparse_to_dense/sparse/main.py
sparse_to_dense/sparse/utils/labeling.py
sparse_to_dense/sparse/utils/splitting.py
sparse_to_dense/submodules/video-splitter/.gitignore
sparse_to_dense/submodules/video-splitter/LICENSE
sparse_to_dense/submodules/video-splitter/README.md
sparse_to_dense/submodules/video-splitter/ffmpeg-split.py
sparse_to_dense/submodules/video-splitter/examples/manifest.csv
sparse_to_dense/submodules/video-splitter/examples/manifest.json
sparse_to_dense/utils/videocopy.py
sparse_to_dense-0.0.1.dist-info/entry_points.txt
sparse_to_dense-0.0.1.dist-info/WHEEL
sparse_to_dense-0.0.1.dist-info/METADATA
sparse_to_dense-0.0.1.dist-info/RECORD
