Metadata-Version: 2.1
Name: sparse_to_dense
Version: 0.0.1
Summary: labeling tool for autosink project
Author-email: Janghoo Lee <dlwkdgn1@naver.com>, Subin Jang <subinaksl@naver.com>, Seokwoo Ahn <patrick0503@naver.com>, Dahyun Kim <builtforlove@naver.com>
Requires-Python: >=3.8
Classifier: License :: OSI Approved :: MIT License
Requires-Dist: pick
Requires-Dist: anytree
Requires-Dist: opencv-python
Requires-Dist: natsort
Requires-Dist: streamlit
Requires-Dist: flit ; extra == "dev"
Requires-Dist: pylint ; extra == "dev"
Requires-Dist: yapf ; extra == "dev"
Requires-Dist: python-dotenv ; extra == "dev"
Requires-Dist: requests ; extra == "dev"
Provides-Extra: dev
